Metadata-Version: 2.4
Name: petrosa-data-manager-client
Version: 1.0.50
Summary: Data integrity, intelligence, and distribution hub for the Petrosa trading ecosystem
Home-page: https://github.com/petrosa/petrosa-data-manager
Author: Petrosa Systems
Author-email: Petrosa Systems <info@petrosa.com>
License: MIT
Classifier: Development Status :: 4 - Beta
Classifier: Intended Audience :: Developers
Classifier: License :: OSI Approved :: MIT License
Classifier: Programming Language :: Python :: 3.11
Classifier: Programming Language :: Python :: 3.12
Requires-Python: >=3.8
Requires-Dist: nats-py>=2.7.0
Requires-Dist: fastapi>=0.109.0
Requires-Dist: uvicorn[standard]>=0.27.0
Requires-Dist: sqlalchemy>=2.0.0
Requires-Dist: asyncpg>=0.29.0
Requires-Dist: motor>=3.3.0
Requires-Dist: pymongo>=4.6.0
Requires-Dist: pandas>=2.2.0
Requires-Dist: numpy>=1.26.0
Requires-Dist: pydantic>=2.5.0
Requires-Dist: pydantic-settings>=2.1.0
Requires-Dist: structlog>=24.1.0
Requires-Dist: opentelemetry-api>=1.22.0
Requires-Dist: opentelemetry-sdk>=1.22.0
Requires-Dist: opentelemetry-instrumentation-fastapi>=0.43b0
Requires-Dist: opentelemetry-exporter-otlp>=1.22.0
Requires-Dist: prometheus-client>=0.19.0
Requires-Dist: httpx>=0.26.0
Requires-Dist: python-json-logger>=2.0.7
Requires-Dist: aiofiles>=23.2.1
Requires-Dist: scipy>=1.12.0
Provides-Extra: dev
Requires-Dist: pytest>=8.0.0; extra == "dev"
Requires-Dist: pytest-asyncio>=0.23.0; extra == "dev"
Requires-Dist: pytest-cov>=4.1.0; extra == "dev"
Requires-Dist: pytest-mock>=3.12.0; extra == "dev"
Requires-Dist: black>=24.1.0; extra == "dev"
Requires-Dist: flake8>=7.0.0; extra == "dev"
Requires-Dist: ruff>=0.2.0; extra == "dev"
Requires-Dist: mypy>=1.8.0; extra == "dev"
Requires-Dist: bandit>=1.7.6; extra == "dev"
Requires-Dist: types-aiofiles>=23.2.0; extra == "dev"
Dynamic: author
Dynamic: home-page
Dynamic: requires-python
